kubernetes_utils/Configuration.py
kubernetes_utils/Resources.py
kubernetes_utils/SpecFactory.py
kubernetes_utils/__init__.py
kubernetes_utils-0.0.2.dist-info/LICENSE
kubernetes_utils-0.0.2.dist-info/METADATA
kubernetes_utils-0.0.2.dist-info/WHEEL
kubernetes_utils-0.0.2.dist-info/top_level.txt
kubernetes_utils-0.0.2.dist-info/zip-safe
kubernetes_utils-0.0.2.dist-info/RECORD
